nano_vectordb/__init__.py
nano_vectordb/dbs.py
nano_vectordb-0.0.4.2.dist-info/METADATA
nano_vectordb-0.0.4.2.dist-info/WHEEL
nano_vectordb-0.0.4.2.dist-info/top_level.txt
nano_vectordb-0.0.4.2.dist-info/RECORD
