Metadata-Version: 2.1
Name: nano-vectordb
Version: 0.0.4.2
Summary: A simple, easy-to-hack Vector Database implementation
Home-page: https://github.com/gusye1234/nano-vectordb
Author: JianbaiYe
Classifier: Programming Language :: Python :: 3
Classifier: License :: OSI Approved :: MIT License
Classifier: Operating System :: OS Independent
Requires-Python: >=3.9
Requires-Dist: numpy
